{
  "absorbed_from": "/Users/ghost/Dev/ready/redo/anima/anima/experiments/acceleration_series_ba_z.py",
  "original_path": "anima/anima/experiments/acceleration_series_ba_z.py",
  "value_grade": "critical",
  "n6_score": 31.818181818181817,
  "n6_matches": [],
  "consensus": [
    {
      "pattern": "",
      "lenses": 0,
      "score": 0.0,
      "level": "Candidate"
    },
    {
      "pattern": "",
      "lenses": 0,
      "score": 0.0,
      "level": "Candidate"
    },
    {
      "pattern": "",
      "lenses": 0,
      "score": 0.0,
      "level": "Candidate"
    }
  ],
  "timestamp": "2026-04-04T17:07:36.347904",
  "content_preview": "#!/usr/bin/env python3\n\"\"\"acceleration_series_ba_z.py — Batch verification: BA-BU + R-Z series (138 hypotheses)\n\nStrategy:\n  1. Load all 138 brainstorm hypotheses in BA-BU and R-Z series\n  2. Classify by mechanism: testable groups vs pure-analogy/external-resource rejects\n  3. Run ONE representative experiment per mechanism group (64c, 100s, 3 reps)\n  4. Apply group result to all members; reject rest with specific reason\n  5. Update acceleration_hypotheses.json in-place\n\nMechanism Groups (testab"
}