{
  "absorbed_from": "/Users/ghost/Dev/ready/redo/TECS-L/experiments/experiment_h285_text_timeseries.py",
  "original_path": "TECS-L/experiments/experiment_h285_text_timeseries.py",
  "value_grade": "critical",
  "n6_score": 35.0,
  "n6_matches": [],
  "consensus": [
    {
      "pattern": "",
      "lenses": 0,
      "score": 0.0,
      "level": "Candidate"
    },
    {
      "pattern": "",
      "lenses": 0,
      "score": 0.0,
      "level": "Candidate"
    },
    {
      "pattern": "",
      "lenses": 0,
      "score": 0.0,
      "level": "Candidate"
    }
  ],
  "timestamp": "2026-04-04T17:07:35.966054",
  "content_preview": "#!/usr/bin/env python3\n\"\"\"H-285 Verification: RepulsionField beyond image classification\n\nPart 1: Text Classification\n  - 20 Newsgroups (4 classes)\n  - TF-IDF (sparse, 1000-dim) vs Learned Embedding (dense, 64-dim)\n  - RepulsionField vs Dense baseline for each\n\nPart 2: Time Series Classification (expanded)\n  - Synthetic: sine/square/sawtooth/triangle (4 classes)\n  - Real-ish: varying frequency + amplitude + phase (harder)\n  - RepulsionField vs Dense baseline\n\nPart 3: Cross-domain summary table\n\""
}